sandra/__init__.py
sandra/ontology.py
sandra/reasoner.py
sandra/torch.py
sandra_py-0.1.2.dist-info/LICENSE
sandra_py-0.1.2.dist-info/METADATA
sandra_py-0.1.2.dist-info/WHEEL
sandra_py-0.1.2.dist-info/top_level.txt
sandra_py-0.1.2.dist-info/RECORD
